aisec/__init__.py
aisec/aisec.py
examples/__init__.py
examples/basic_usage.py
examples/batch_detection.py
tests/__init__.py
tests/test_aisec.py
aisec_sdk-0.2.0.dist-info/METADATA
aisec_sdk-0.2.0.dist-info/WHEEL
aisec_sdk-0.2.0.dist-info/top_level.txt
aisec_sdk-0.2.0.dist-info/RECORD
